client/__init__.py
client/prometeo_client.py
controllers/__init__.py
controllers/configuration_controller.py
controllers/prometeo_controller.py
exceptions/ConfigException.py
exceptions/ProviderNotFound.py
exceptions/SessionException.py
exceptions/__init__.py
helpers/__init__.py
helpers/crypto.py
helpers/profiler.py
helpers/session_handler.py
helpers/table_helper.py
pmo/__init__.py
pmo/__main__.py
pmo/prometeo.py
prometeo_cli-1.0.1.dist-info/METADATA
prometeo_cli-1.0.1.dist-info/WHEEL
prometeo_cli-1.0.1.dist-info/top_level.txt
prometeo_cli-1.0.1.dist-info/RECORD
