Metadata-Version: 2.1
Name: prometeo-cli
Version: 1.0.1
Summary: CLI Tool for the Prometeo Open Banking API
Home-page: https://github.com/dieg0moraes/prometeo-cli
Author: Diego Moraes
Author-email: dmoraes11cb@gmail.com
License: UNKNOWN
Platform: UNKNOWN
Classifier: Programming Language :: Python :: 3
Classifier: Operating System :: OS Independent
